{
  "headlines": [
    {
      "title": "巴哈姆特 30 週年系列報導 一窺數據勇者的史詩傳說！",
      "url": "https://gnn.gamer.com.tw/detail.php?sn=305788"
    },
    {
      "title": "《SD 鋼彈 G 世代 永恆》釋出新單位 UR「夜鶯 (EX)」「ν 鋼彈(雙翼狀感應砲裝備型) (EX)」登場預告",
      "url": "https://gnn.gamer.com.tw/detail.php?sn=305743"
    },
    {
      "title": "中國都市開放世界抓寵 RPG《望月》釋出實機跑圖預告片 將於中國舉辦線下試玩會",
      "url": "https://gnn.gamer.com.tw/detail.php?sn=305724"
    },
    {
      "title": "系列新作《決勝時刻：現代戰爭 IV》正式亮相 彷彿頭條新聞般的韓戰即將爆發",
      "url": "https://gnn.gamer.com.tw/detail.php?sn=305689"
    },
    {
      "title": "《鬥陣特攻》x YOASOBI 宣布合作　將推出專屬新歌《Orion》、專屬動畫 MV 與聯名造型等",
      "url": "https://gnn.gamer.com.tw/detail.php?sn=305653"
    },
    {
      "title": "受記憶體和儲存成本提高影響　Valve 宣布 Steam Deck OLED 價格調漲 40%",
      "url": "https://gnn.gamer.com.tw/detail.php?sn=305613"
    },
    {
      "title": "維梅爾「戴珍珠耳環的少女」日本畫展與《米飛兔》以及《芙莉蓮》展開合作",
      "url": "https://gnn.gamer.com.tw/detail.php?sn=305605"
    },
    {
      "title": "《勇者鬥惡龍 XII》推翻原案重啟開發 變更副標題並回歸系列傳統風格",
      "url": "https://gnn.gamer.com.tw/detail.php?sn=305600"
    }
  ],
  "boards": [
    {
      "name": "卡厄思夢境",
      "posts": [
        {
          "title": "【討論】沒想到出擊一周免費數量直接從補三個變成補9個了",
          "url": "C.php?bsn=80099&snA=5184&tnum=1",
          "time": "33 分前",
          "brief": "不知道有沒有人覺得是補三個，然後爆掉的 笑門這次誇張了"
        },
        {
          "title": "【心得】【麥格納主C】『全程無傷螺旋塔150層』（內附存檔分享）",
          "url": "C.php?bsn=80099&snA=5183&tnum=1",
          "time": "4 小時前",
          "brief": "上一編文章︰【心得】【友紀主C】『攻略螺旋塔150層』（內附存檔分享） 又是我，繼上次我們堆士氣讓友紀打通150螺旋塔，這次我們來堆決心來幫是麥格納當主c打螺旋塔150。 老實"
        },
        {
          "title": "【情報】骰子活動那兩個腦殘成就的出處",
          "url": "C.php?bsn=80099&snA=5182&tnum=1",
          "time": "4 小時前",
          "brief": "我是走到這問號 觸發了一個受邀參加慶典的事件 他直接帶我到慶典那一格 其他問號有沒有同樣效果我就不知道了 活動根本在搞"
        },
        {
          "title": "【問題】阿黛海特最後一個故事 隱藏boss",
          "url": "C.php?bsn=80099&snA=5175&tnum=2",
          "time": "6 小時前",
          "brief": "有人知道這是哪隻boss嗎？ 弄那個石碑的也不對！！"
        },
        {
          "title": "【問題】回鍋請益",
          "url": "C.php?bsn=80099&snA=5181&tnum=1",
          "time": "6 小時前",
          "brief": "各位好 之前在天使前退坑 現在沒事想回來看看 下載回來之後發現時間很尷尬.. 自選跟市長那些都剛好結束了 想向各位請教一下一些事情 由於這次回來看蠻喜歡市長的 原本是打算買"
        },
        {
          "title": "【問題】請問複製選項 請大佬幫幫我（在線等",
          "url": "C.php?bsn=80099&snA=5180&tnum=1",
          "time": "昨天 22:33",
          "brief": "市長目前 pt 160/180複製兩張 如果在複製劍之雨或展開極光的話是會變成200pt 把刪除的護盾補回來變成180pt嗎？ 劍之雨展開極光推薦選哪一個呢 還是我乖乖選創造與破壞 還是可以局外"
        },
        {
          "title": "【閒聊】友紀 卡牌大改預想",
          "url": "C.php?bsn=80099&snA=5179&tnum=1",
          "time": "昨天 16:15",
          "brief": "友紀明明這麼有實力 她值得更強的機體 作為剛出就抽了2+1的我 現在她只能在封面當裝飾品十分悲傷 友紀她的主要機制就是\"靈感\"，與她一言難盡的破冰斬 所以決定幫她重新"
        },
        {
          "title": "【閒聊】爆檔後的存檔",
          "url": "C.php?bsn=80099&snA=5178&tnum=1",
          "time": "昨天 12:32",
          "brief": "變成這樣了，貌似好像還能用用？各位大佬看看怎麼樣"
        },
        {
          "title": "【攻略】我也想跟市長連結，不是公主連結，海德瑪麗攻略慢慢更 5/18優化邊境極光流",
          "url": "C.php?bsn=80099&snA=4841&tnum=73",
          "time": "昨天 09:00",
          "brief": "對不起拖稿了 需要力量打文 更新日誌: 4/28大家好我是水梨，今天先上中立閃跟神閃，我會慢慢把文章補齊 大概一個月內都會不斷更新，明天抽完先雲構築，雲完開始刷存檔 有存檔"
        },
        {
          "title": "【心得】S3目前T0體系 \"夢之邊境\" 雨果小丑+市長(多段C) 上限很高 一般即可使用",
          "url": "C.php?bsn=80099&snA=4995&tnum=36",
          "time": "昨天 03:40",
          "brief": "開發者 之前的兔狙市長追擊流 WOYIA 原視頻:卡厄思梦境正式进入自动化时代！我说梦之边境好牌多拿，拿够了牌库自己会打游戏 機制不想懂沒關係，反正牌會自己亂飛，更懶的話可"
        },
        {
          "title": "【心得】【友紀主C】『攻略螺旋塔150層』（內附存檔分享）",
          "url": "C.php?bsn=80099&snA=5177&tnum=1",
          "time": "昨天 01:55",
          "brief": "刷了一天終於把友紀的存檔搞好了，真的累。 先附存檔： 友紀（主c）6+6 1.基本上主要卡牌偷襲斬最好就拿士氣3，命座高可以像我拿脆弱也可以。 2.必帶一張主宰者怪物卡。 3.迷惑"
        }
      ]
    },
    {
      "name": "闇影詩章 Shadowverse",
      "posts": [
        {
          "title": "【情報】5/28卡片能力變更相關事宜 維護期間 2026年5月28日 13:00 ～ 16:00（UTC+8）",
          "url": "C.php?bsn=29330&snA=27629&tnum=19",
          "time": "6 小時前",
          "brief": ""
        },
        {
          "title": "【閒聊】[無限制] 妖精跟主教卡組分享",
          "url": "C.php?bsn=29330&snA=27638&tnum=1",
          "time": "昨天 21:09",
          "brief": "有在聊天室的都知道我相當菜，平常就只是登入解每日， 而且我大多時間都關掉CR在打，EPIC那些升降接太閃了， 只是無限制 真的沒啥人在玩，卡組資料甚麼都相當少， 不過也因此"
        },
        {
          "title": "【問題】Master cup優勝! BO3倒地 更新牌組",
          "url": "C.php?bsn=29330&snA=27633&tnum=4",
          "time": "昨天 16:51",
          "brief": "大家好，本人今天有幸9-1晉級星期日的BO3(也太趕) 因為是第一次晉級這種比賽 想找個伴確認注意事項 他的app只有日文怕漏看了 要做的事情應該是: 下載Navigator並且連動遊戲帳號，加"
        },
        {
          "title": "【閒聊】邪神紀念碑",
          "url": "C.php?bsn=29330&snA=27597&tnum=2",
          "time": "昨天 09:08",
          "brief": "0.,0 身為一個每天只在無限制區玩邪神當作測當日運勢的怪咖， 感覺有必要紀念一下那些慘死在邪神手下的烈士(衰鬼)們。 基本上只節錄邪神出來翻桌的片段，除非整場過程太過經典"
        },
        {
          "title": "【繪圖】跟夜魔大人對局的感覺是這樣的",
          "url": "C.php?bsn=29330&snA=27635&tnum=2",
          "time": "昨天 08:21",
          "brief": "這張是在砍貓後 5/28調整戀人之前畫的 砍貓後拚盡全力依然不能讓夜魔大人盡興 雖然不知道戀人被+1費後是不是還能舞就是"
        },
        {
          "title": "【攻略】全職業Byd挑戰中！T1進化中夜牌組推薦",
          "url": "C.php?bsn=29330&snA=27637&tnum=1",
          "time": "昨天 00:39",
          "brief": "前言：大家好，我是Tgznzz，目前在挑戰全職Byd中。 這次介紹的是進化中夜，之後也會陸續補上挑戰成功的牌組。 牌組： 這套構築目前是優開中速夜、皇家和造物仇，不利龍、教。"
        }
      ]
    },
    {
      "name": "明日方舟",
      "posts": [
        {
          "title": "【攻略】界園DLC1電表倒轉機制圖文解說",
          "url": "C.php?bsn=33651&snA=12398&tnum=1",
          "time": "5 小時前",
          "brief": "什麼是電表倒轉? 電表倒轉是界園肉鴿中利用機制錢滾錢、生命滾生命，從而達到全藏品搶到績老闆只剩熱水壺能賣你的玩法戲稱。由於形似左腳踩右腳上宇宙、虛空發電，故而得此"
        },
        {
          "title": "【情報】【泡影蒼霆】活動內容前瞻",
          "url": "C.php?bsn=33651&snA=12397&tnum=1",
          "time": "昨天 17:06",
          "brief": "梓蘭和空爆再次睜開眼，周圍的一切都是那麼地陌生—— 泡普卡，斑點，月見夜？為什麼你們看起來和平時不太一樣？ 泡影國，詛咒，禦輪？羅德島的資料庫中可沒有類似的記載。"
        },
        {
          "title": "【情報】【陸服】模組升級系統內容前瞻//部分模組升級效果前瞻-持續更新中【泡影蒼霆】版本",
          "url": "C.php?bsn=33651&snA=7442&tnum=53",
          "time": "昨天 15:06",
          "brief": "//大家好 這裡是明日方舟項目組。 在即將到來的版本更新中，【模組升級】系統將隨之上線。 【模組升級】系統上線後，部分界面也將在現有的基礎上進行優化，您可以通過對應界"
        },
        {
          "title": "【攻略】薩卡茲的無終奇語N18二四五超大蛋－擬態死仇酒神開局攻略",
          "url": "C.php?bsn=33651&snA=12396&tnum=9",
          "time": "昨天 13:06",
          "brief": "大家好我是Cure，是的，沒錯，我又來了，帶著薩卡茲攻略回來了。 你也許對我有印象，可能是個堅定的繁中服加速支持者？又或者，是個每年都會發文的廚力放出者舟批？又或許，"
        },
        {
          "title": "【心得】個人(新手)視角推薦的sidestory開啟順序",
          "url": "C.php?bsn=33651&snA=12395&tnum=1",
          "time": "昨天 02:43",
          "brief": "主要是這種文章我不確定要查甚麼關鍵字也沒太多印象 想說自己發一篇 如果新手有看到的話可以稍微避嫌一些比較雷的sidestory 理智的部分我自己有打得差不多的程度 才會列出來該ss"
        }
      ]
    },
    {
      "name": "明日方舟：終末地",
      "posts": [
        {
          "title": "【閒聊】弭弗是不是被編劇討厭了?",
          "url": "C.php?bsn=74604&snA=3930&tnum=4",
          "time": "1 小時前",
          "brief": "洛茜與管理員的夫妻照(X) 一條一條的理由慢慢梳理 1.北方大遠征因背叛者導致失敗，侵蝕潮衝到武陵造成宏山科院死了一堆人，導致武陵異常混亂 同時導致清波寨的物資大缺，清波"
        },
        {
          "title": "【問題】能入坑嗎？",
          "url": "C.php?bsn=74604&snA=3931&tnum=8",
          "time": "2 小時前",
          "brief": "各位板大好 最近也在考慮入坑終末地 被莊方宜吸引到 有玩過方舟一段時間（角色夕~水月肉鴿出之前） 想請問這款遊戲的養成是''正''提升嗎？ 比如強化素材多少就是"
        },
        {
          "title": "【閒聊】四號谷地是不是乏人問津了",
          "url": "C.php?bsn=74604&snA=3932&tnum=1",
          "time": "2 小時前",
          "brief": "四號谷地的集成工業區域最多也最大 但其實到目前為止 除了前期還沒進武陵之前的一些基建跟裝備都需要再谷地完成 但進武陵之後好像幾乎都沒四號谷地的事情了 就連活動都是以"
        },
        {
          "title": "洛潔羊隊 競速90聶菲斯之研究。1樓近戰主控45秒結束；5樓遠程主控33秒達成，心得後補",
          "url": "C.php?bsn=74604&snA=3915&tnum=5",
          "time": "3 小時前",
          "brief": "這樓是用洛西主控打45秒的心得文 5樓用遠程主控打33秒達成，心得文之後補 - 研究了一個月，由最初76s>64s>61s>58s>57s>56s>54-55s>50s>47s>45s， 真的是洛西主控的極限了"
        },
        {
          "title": "【閒聊】佩麗卡腳上的對講機是．．．？",
          "url": "C.php?bsn=74604&snA=3924&tnum=8",
          "time": "6 小時前",
          "brief": "看到b站有人錄了佩麗卡的腳步聲ASMR的影片才發現 佩麗卡腳上有綁一個對講機??? 這是要回傳腳步聲的意思嗎XD 這個對講機的用意到底是甚麼哈哈哈"
        },
        {
          "title": "【情報】《明日方舟：終末地》紀念插畫集 Vol.1 即將開售",
          "url": "C.php?bsn=74604&snA=3354&tnum=3",
          "time": "6 小時前",
          "brief": "該說不愧是鷹角嗎... 這麼快！才開服三個月不到就出插畫集了～ 定價：99 RMB 規格：大 16 開 軟精裝 特典：鐳射卡×2、透卡×2 時間：2026/04/21 開始預售（預計 2026/06 發貨） https://detail"
        },
        {
          "title": "【閒聊】1.3即將到來，危機合約讓我陷入選隊煩惱",
          "url": "C.php?bsn=74604&snA=3929&tnum=3",
          "time": "6 小時前",
          "brief": "目前僅專心練了雷隊，像是主副C莊方宜和佩麗卡，再練控場、潔哥和小羊輔，之前火隊沒有練很高，剩下幾乎沒什麼養，稍微爬近期方舟危機合約，有熟方舟危機合約的大大，能照"
        },
        {
          "title": "【閒聊】你們有沒有思考過終末地能源學",
          "url": "C.php?bsn=74604&snA=3908&tnum=5",
          "time": "昨天 21:36",
          "brief": "一般情況下 一顆電池大概就夠你幾台設備產線跑幾分鐘 但放進戰爭機器裡 他們就會機魂狂喜，維持半年以上全天候開機智能火控鎖敵並且還能從空氣中搓出彈藥 看迫擊炮刷基質有"
        },
        {
          "title": "【閒聊】輝光池有滿潛，會為了1.3轉物理隊抽池嗎？",
          "url": "C.php?bsn=74604&snA=3899&tnum=11",
          "time": "昨天 20:11",
          "brief": "乳題 我是被1.3前瞻弭弗的大痣，不、是大志所吸引 掙扎血魔還是弭弗間，最後選擇全婆！！ 物理隊也想好了，應該不全走官方推的：弭/千/駿/燼，到時看看怎麼湊好 但在輝光池已"
        },
        {
          "title": "【閒聊】第一個限定男角是挺帥的拉~",
          "url": "C.php?bsn=74604&snA=3876&tnum=21",
          "time": "昨天 19:16",
          "brief": "看完版本前瞻後發現除了弭弗還有卡謬 招式演練就是那種大開大合而且速度也不差 如果要說操作手感的話應該是有的 只是強度就還不知道? 但畢竟是第一個限定男角應該不會太弱?"
        },
        {
          "title": "【繪圖】潔爾佩塔",
          "url": "C.php?bsn=74604&snA=3928&tnum=1",
          "time": "昨天 19:06",
          "brief": "還在泰拉的時候潔哥就是我第一隻6星 當時對她沒沒什麼興趣 到最近朋友聊到才被科普了他的故事 畫完才發現 不對阿 塔位二還沒有現代都市阿... 看來不是回到龍門就是帝江號有「"
        },
        {
          "title": "【閒聊】看到很好笑的二創分享一下",
          "url": "C.php?bsn=74604&snA=3183&tnum=12",
          "time": "昨天 19:05",
          "brief": "整個蘋果也算了,現在管管是開始吃電線了嗎?"
        },
        {
          "title": "【閒聊】終末地官方社群 各國有不同莊方宜人物QA 小動畫",
          "url": "C.php?bsn=74604&snA=3918&tnum=5",
          "time": "昨天 17:06",
          "brief": "剛剛才發現雖然官方社群的發文基本雷同，但各語言有差異的部分(繁中／日文／英文／俄羅斯／韓語等等) NGA的翻譯帖 以這次《終末地AskMeAnything特別活動》回顧 來說，繁中／英文／"
        },
        {
          "title": "【情報】生物檔案 | 藏劍谷",
          "url": "C.php?bsn=74604&snA=3926&tnum=3",
          "time": "昨天 13:52",
          "brief": "資料來源：官方Ｘ 藏劍谷的深處，注意猛獸出沒。"
        },
        {
          "title": "【問題】武陵請問有幾個據點？",
          "url": "C.php?bsn=74604&snA=3921&tnum=4",
          "time": "昨天 06:56",
          "brief": "如題，主線都通關了只有天王坪和武陵城是對的嗎請問還有其他據點嗎"
        },
        {
          "title": "【情報】官方漫畫《加油吧！終末地》——「第5話」",
          "url": "C.php?bsn=74604&snA=3923&tnum=3",
          "time": "昨天 01:54",
          "brief": "來源 : 終末地 官方FB 官方漫畫《加油吧！終末地》——「第5話」"
        }
      ]
    },
    {
      "name": "看板 81566 (Error)",
      "posts": []
    },
    {
      "name": "世界計畫 繽紛舞台！ feat. 初音未來",
      "posts": [
        {
          "title": "【攻略】現時四星列表 (圖多注意) (更新至206期)",
          "url": "C.php?bsn=37505&snA=404&tnum=65",
          "time": "昨天 11:44",
          "brief": "(更新至206期) 全一覧以團體，屬性，技能分類 排列組合：(團員/屬性) (特殊) 虚擬歌手會放在其卡片相對應的團體後面， 若果其團體沒有該虚擬歌手將會直接略過而不留上空格 *所有"
        }
      ]
    },
    {
      "name": "雀魂麻將majsoul",
      "posts": [
        {
          "title": "【情報】雀魂麻將「國際中文服」四人團體賽【英豪戰】[總決賽]",
          "url": "C.php?bsn=36476&snA=4019&tnum=6",
          "time": "昨天 11:14",
          "brief": "雀魂麻將國際中文服四人團體賽【英豪戰】即將開啓！ 一、報名與參賽資格 【報名時間】2026年4月28日-5月10日 23:59 (UTC+8) 【參賽條件】 以四人一隊的團隊形式報名，所有成員均達到"
        },
        {
          "title": "【情報】《雀魂麻將 majsoul》「白石奈々」2026 年 官方生日賀圖",
          "url": "C.php?bsn=36476&snA=4040&tnum=1",
          "time": "昨天 11:04",
          "brief": "5 月 31 日為《雀魂麻將 majsoul》 「白石奈々」的生日 為此紀念官方於 X（推特）釋出 由「hidis」送上的生日賀圖"
        },
        {
          "title": "【閒聊】來分享一下各位和到或遇到的大牌吧",
          "url": "C.php?bsn=36476&snA=24&tnum=1467",
          "time": "昨天 10:01",
          "brief": "先來個鎮樓的 強者我朋友九巡和牌 這輩子大概只會看到這一次"
        }
      ]
    },
    {
      "name": "緋染天空 Heaven Burns Red",
      "posts": [
        {
          "title": "【問題】剛玩，請求健檢",
          "url": "C.php?bsn=37697&snA=5035&tnum=3",
          "time": "昨天 15:58",
          "brief": "不好意思，剛玩新手 新手剛玩，因為剛玩不太清楚 請求健檢，先謝謝各位大大 無課微小課休閒玩家 我要練那個？或抽卡2個池那個池佳？（已解決） 還在存保底中，目前9000星了（30"
        }
      ]
    }
  ],
  "generatedAt": "2026/6/1 上午7:00:06"
}